pybonsai/__init__.py
pybonsai/__main__.py
pybonsai/animations.py
pybonsai/colors.py
pybonsai/draw.py
pybonsai/radio.py
pybonsai/tree.py
pybonsai/utils.py
pybonsai/tests/.gitkeep
pybonsai-2.1.0.dist-info/METADATA
pybonsai-2.1.0.dist-info/WHEEL
pybonsai-2.1.0.dist-info/entry_points.txt
pybonsai-2.1.0.dist-info/licenses/LICENSE
pybonsai-2.1.0.dist-info/RECORD
