Metadata-Version: 2.4
Name: pybonsai
Version: 2.1.0
Summary: PyBonsai procedurally generates ASCII art bonsai trees in your terminal.
Project-URL: Homepage, https://github.com/DaEtoJostka/PyBonsai-CLI
Project-URL: Original, https://github.com/Ben-Edwards44/PyBonsai
Author-email: Ivan Karlov <karlovivan679@gmail.com>
License: MIT
License-File: LICENSE
Keywords: ascii,bonsai,cli,pybonsai,terminal,tree
Classifier: Operating System :: OS Independent
Classifier: Programming Language :: Python :: 3.9
Classifier: Programming Language :: Python :: 3.10
Classifier: Programming Language :: Python :: 3.11
Classifier: Programming Language :: Python :: 3.12
Requires-Python: >=3.9
